ailment/__init__.py
ailment/block.py
ailment/block_walker.py
ailment/constant.py
ailment/converter_common.py
ailment/converter_pcode.py
ailment/converter_vex.py
ailment/expression.py
ailment/manager.py
ailment/py.typed
ailment/statement.py
ailment/tagged_object.py
ailment/utils.py
ailment-9.2.158.dist-info/licenses/LICENSE
ailment-9.2.158.dist-info/METADATA
ailment-9.2.158.dist-info/WHEEL
ailment-9.2.158.dist-info/top_level.txt
ailment-9.2.158.dist-info/RECORD
